YoutubeDownloader/__init__.py
YoutubeDownloader/downloader.py
Aurora_YTDownload-1.0.0.dist-info/LICENSE
Aurora_YTDownload-1.0.0.dist-info/METADATA
Aurora_YTDownload-1.0.0.dist-info/WHEEL
Aurora_YTDownload-1.0.0.dist-info/top_level.txt
Aurora_YTDownload-1.0.0.dist-info/RECORD
