Metadata-Version: 2.1
Name: Aurora-YTDownload
Version: 1.0.0
Summary: Python package to download Videos from Youtube
Author: Zockerwolf76
Author-email: 
Classifier: Programming Language :: Python :: 3
Requires-Python: >=3.6
License-File: LICENSE
